callbacks/__init__.py
callbacks/trainingmonitor.py
datasets/__init__.py
datasets/simpledatasetloader.py
juggle-0.1.data/scripts/juggle
preprocessing/__init__.py
preprocessing/imagetoarraypreprocessor.py
preprocessing/simplepreprocessor.py
utils/__init__.py
utils/captchahelper.py
juggle-0.1.dist-info/LICENSE
juggle-0.1.dist-info/METADATA
juggle-0.1.dist-info/WHEEL
juggle-0.1.dist-info/top_level.txt
juggle-0.1.dist-info/RECORD
