Metadata-Version: 2.1
Name: juggle
Version: 0.1
Summary: Deep Learning Tools for Computer Vision and More
Home-page: https://github.com/laygond/Juggle-Deep-Tools
Author: Bryan Laygond
Author-email: laygond@gmail.com
License: UNKNOWN
Platform: UNKNOWN
Classifier: Programming Language :: Python :: 3
Classifier: License :: OSI Approved :: MIT License
Classifier: Operating System :: OS Independent
